tdp_publicdb/__init__.py
tdp_publicdb/data.py
tdp_publicdb/entity.py
tdp_publicdb/pg_agg_score.py
tdp_publicdb/query_common.py
tdp_publicdb/query_drug.py
tdp_publicdb/query_gene.py
tdp_publicdb/query_sample.py
tdp_publicdb/query_score.py
tdp_publicdb/settings.py
tdp_publicdb/sql.py
tdp_publicdb/__pycache__/__init__.cpython-310.pyc
tdp_publicdb/__pycache__/data.cpython-310.pyc
tdp_publicdb/__pycache__/entity.cpython-310.pyc
tdp_publicdb/__pycache__/pg_agg_score.cpython-310.pyc
tdp_publicdb/__pycache__/query_common.cpython-310.pyc
tdp_publicdb/__pycache__/query_drug.cpython-310.pyc
tdp_publicdb/__pycache__/query_gene.cpython-310.pyc
tdp_publicdb/__pycache__/query_sample.cpython-310.pyc
tdp_publicdb/__pycache__/query_score.cpython-310.pyc
tdp_publicdb/__pycache__/settings.cpython-310.pyc
tdp_publicdb/__pycache__/sql.cpython-310.pyc
tdp_publicdb/migration/README
tdp_publicdb/migration/env.py
tdp_publicdb/migration/script.py.mako
tdp_publicdb/migration/versions/20200302_1312_b477004c3673_First_Revision.py
tdp_publicdb/migration/versions/20200420_0912_4c6cb36e57e0_add_additional_tissue_columns.py
tdp_publicdb/migration/versions/20200420_1044_dd7c97913940_add_additional_cellline_columns.py
tdp_publicdb/migration/versions/20200603_0631_9ed460a9ea4a_add_drugscore_view.py
tdp_publicdb/migration/versions/20200908_0609_e40e7676eb1c_add_gene_signature_views.py
tdp_publicdb/migration/versions/20211118_1048_ec6a94da4809_add_scientificname_to_tdp_drug.py
tdp_publicdb/migration/versions/20220614_1244_5a8dc3921597_new_depletion_scores.py
tdp_publicdb/migration/versions/assets/ordino-hg38-schema-postgres12.sql
tdp_publicdb/tests/__init__.py
tdp_publicdb/tests/conftest.py
tdp_publicdb/tests/test_main_app.py
tdp_publicdb/tests/__pycache__/__init__.cpython-310.pyc
tdp_publicdb/tests/__pycache__/conftest.cpython-310-pytest-7.2.1.pyc
tdp_publicdb/tests/__pycache__/test_main_app.cpython-310-pytest-7.2.1.pyc
tdp_publicdb-13.1.1.dist-info/LICENSE
tdp_publicdb-13.1.1.dist-info/METADATA
tdp_publicdb-13.1.1.dist-info/WHEEL
tdp_publicdb-13.1.1.dist-info/entry_points.txt
tdp_publicdb-13.1.1.dist-info/top_level.txt
tdp_publicdb-13.1.1.dist-info/RECORD
