Metadata-Version: 2.1
Name: tdp-publicdb
Version: 13.1.1
Home-page: https://ordino.caleydoapp.org
Author: The Caleydo Team
Author-email: contact@caleydo.org
License: BSD-3-Clause
Classifier: Intended Audience :: Developers
Classifier: Operating System :: OS Independent
Classifier: License :: OSI Approved :: BSD License
Classifier: Programming Language :: Python
Classifier: Programming Language :: Python :: 3.10
Requires-Python: >=3.10
License-File: LICENSE
Requires-Dist: tdp-core (<18.0.0,>=17.0.0)
Provides-Extra: develop
Requires-Dist: black (~=22.12.0) ; extra == 'develop'
Requires-Dist: pyright (~=1.1.285) ; extra == 'develop'
Requires-Dist: pytest-runner (~=6.0.0) ; extra == 'develop'
Requires-Dist: pytest (~=7.2.0) ; extra == 'develop'
Requires-Dist: ruff (==0.0.218) ; extra == 'develop'
